p2pd/__init__.py
p2pd/ack_udp.py
p2pd/address.py
p2pd/base_n.py
p2pd/base_stream.py
p2pd/clock_skew.py
p2pd/cmd_tools.py
p2pd/daemon.py
p2pd/echo_server.py
p2pd/errors.py
p2pd/http_client_lib.py
p2pd/http_server_lib.py
p2pd/install.py
p2pd/interface.py
p2pd/ip_range.py
p2pd/irc_dns.py
p2pd/nat.py
p2pd/nat_test.py
p2pd/net.py
p2pd/netiface_extra.py
p2pd/ntp_client.py
p2pd/p2p_addr.py
p2pd/p2p_node.py
p2pd/p2p_pipe.py
p2pd/p2p_protocol.py
p2pd/p2p_utils.py
p2pd/rest_api.py
p2pd/route.py
p2pd/route_table.py
p2pd/settings.py
p2pd/signaling.py
p2pd/sqlite_kvs.py
p2pd/stun_client.py
p2pd/tcp_punch.py
p2pd/test_init.py
p2pd/test_server.py
p2pd/toxiclient.py
p2pd/toxiserver.py
p2pd/turn_client.py
p2pd/turn_defs.py
p2pd/turn_process.py
p2pd/upnp.py
p2pd/utils.py
p2pd/var_names.py
p2pd/win_net.py
p2pd/win_netifaces.py
p2pd/scripts/kvs_schema.sqlite3
p2pd-2.7.9.dist-info/LICENSE
p2pd-2.7.9.dist-info/METADATA
p2pd-2.7.9.dist-info/WHEEL
p2pd-2.7.9.dist-info/top_level.txt
p2pd-2.7.9.dist-info/RECORD
