Metadata-Version: 2.1
Name: p2pd
Version: 2.7.9
Summary: Asynchronous P2P networking library and service
Home-page: http://github.com/robertsdotpm/p2pd
Author: Matthew Roberts
Author-email: matthew@roberts.pm
License: public domain
Keywords: NAT traversal,TCP hole punching,simultaneous open,UPnP,STUN,TURN,SIP,DHCP,add IP to interface,NATPMP,P2P,Peer-to-peer networking library,python
Classifier: Intended Audience :: Developers
Classifier: Programming Language :: Python :: 3
License-File: LICENSE
Requires-Dist: gmqtt ==0.6.11
Requires-Dist: ntplib ==0.4.0
Requires-Dist: aiounittest ==1.4.2
Requires-Dist: xmltodict
Requires-Dist: ecdsa
Requires-Dist: argon2pure
Requires-Dist: aiosqlite
Requires-Dist: netifaces ==0.11.0 ; sys_platform != "win32"
